odoo/addons/account_credit_control_queue_job/README.rst
odoo/addons/account_credit_control_queue_job/__init__.py
odoo/addons/account_credit_control_queue_job/__manifest__.py
odoo/addons/account_credit_control_queue_job/i18n/account_credit_control_queue_job.pot
odoo/addons/account_credit_control_queue_job/i18n/it.po
odoo/addons/account_credit_control_queue_job/models/__init__.py
odoo/addons/account_credit_control_queue_job/models/credit_control_communication.py
odoo/addons/account_credit_control_queue_job/models/credit_control_run.py
odoo/addons/account_credit_control_queue_job/readme/DESCRIPTION.md
odoo/addons/account_credit_control_queue_job/static/description/icon.png
odoo/addons/account_credit_control_queue_job/static/description/index.html
odoo/addons/account_credit_control_queue_job/tests/__init__.py
odoo/addons/account_credit_control_queue_job/tests/test_credit_control_run.py
odoo/addons/account_credit_control_queue_job/wizard/__init__.py
odoo/addons/account_credit_control_queue_job/wizard/res_config_settings.py
odoo/addons/account_credit_control_queue_job/wizard/res_config_settings.xml
odoo_addon_account_credit_control_queue_job-18.0.2.0.0.1.dist-info/METADATA
odoo_addon_account_credit_control_queue_job-18.0.2.0.0.1.dist-info/WHEEL
odoo_addon_account_credit_control_queue_job-18.0.2.0.0.1.dist-info/top_level.txt
odoo_addon_account_credit_control_queue_job-18.0.2.0.0.1.dist-info/RECORD
