Metadata-Version: 2.1
Name: odoo-addon-account_credit_control_queue_job
Version: 18.0.2.0.0.1
Requires-Python: >=3.10
Requires-Dist: odoo-addon-account_credit_control==18.0.*
Requires-Dist: odoo-addon-queue_job_batch==18.0.*
Requires-Dist: odoo==18.0.*
Summary: Account Credit Control
Home-page: https://github.com/OCA/credit-control
License: AGPL-3
Author: 360 ERP, Odoo Community Association (OCA)
Author-email: support@odoo-community.org
Classifier: Programming Language :: Python
Classifier: Framework :: Odoo
Classifier: Framework :: Odoo :: 18.0
Classifier: License :: OSI Approved :: GNU Affero General Public License v3
